{"timestamp": 1693163016.054628, "cpu_times": [{"user": 5222040, "nice": 70530, "sys": 5633510, "idle": 835781080, "irq": 0}, {"user": 5338210, "nice": 78290, "sys": 5605640, "idle": 834858520, "irq": 0}], "cpu_percentage": {"total": {"idle": 1940, "total": 1970, "usage": 1.5228426395939132}, "cores": [{"idle": 980, "total": 990, "usage": 1.0101010101010055}, {"idle": 960, "total": 980, "usage": 2.0408163265306145}]}, "freemem": 7305289728, "totalmem": 8323538944, "system_uptime": 853750.04, "process_uptime": 3495.19316793, "network_stat": {"RX": {"Bytes": 3357422345, "Package": 2856483}, "TX": {"Bytes": 356303186, "Package": 2783699}}, "network_bandwidth": {"RX": {"Bytes": 5495, "Package": 37}, "TX": {"Bytes": 3761, "Package": 32}}}
{"timestamp": 1693163017.05537, "cpu_times": [{"user": 5222060, "nice": 70530, "sys": 5633520, "idle": 835782040, "irq": 0}, {"user": 5338270, "nice": 78290, "sys": 5605660, "idle": 834859450, "irq": 0}], "cpu_percentage": {"total": {"idle": 1890, "total": 2000, "usage": 5.500000000000005}, "cores": [{"idle": 960, "total": 990, "usage": 3.0303030303030276}, {"idle": 930, "total": 1010, "usage": 7.920792079207917}]}, "freemem": 7305355264, "totalmem": 8323538944, "system_uptime": 853751.04, "process_uptime": 3496.193988239, "network_stat": {"RX": {"Bytes": 3357429997, "Package": 2856555}, "TX": {"Bytes": 356312216, "Package": 2783753}}, "network_bandwidth": {"RX": {"Bytes": 7652, "Package": 72}, "TX": {"Bytes": 9030, "Package": 54}}}
{"timestamp": 1693163018.056576, "cpu_times": [{"user": 5222080, "nice": 70530, "sys": 5633540, "idle": 835782980, "irq": 0}, {"user": 5338300, "nice": 78290, "sys": 5605670, "idle": 834860390, "irq": 0}], "cpu_percentage": {"total": {"idle": 1880, "total": 1960, "usage": 4.081632653061229}, "cores": [{"idle": 940, "total": 980, "usage": 4.081632653061229}, {"idle": 940, "total": 980, "usage": 4.081632653061229}]}, "freemem": 7305388032, "totalmem": 8323538944, "system_uptime": 853752.04, "process_uptime": 3497.195122411, "network_stat": {"RX": {"Bytes": 3357437703, "Package": 2856626}, "TX": {"Bytes": 356321491, "Package": 2783807}}, "network_bandwidth": {"RX": {"Bytes": 7706, "Package": 71}, "TX": {"Bytes": 9275, "Package": 54}}}
{"timestamp": 1693163019.057924, "cpu_times": [{"user": 5222120, "nice": 70530, "sys": 5633560, "idle": 835783910, "irq": 0}, {"user": 5338310, "nice": 78290, "sys": 5605690, "idle": 834861350, "irq": 0}], "cpu_percentage": {"total": {"idle": 1890, "total": 1980, "usage": 4.545454545454541}, "cores": [{"idle": 930, "total": 990, "usage": 6.060606060606055}, {"idle": 960, "total": 990, "usage": 3.0303030303030276}]}, "freemem": 7305703424, "totalmem": 8323538944, "system_uptime": 853753.04, "process_uptime": 3498.19646011, "network_stat": {"RX": {"Bytes": 3357445303, "Package": 2856696}, "TX": {"Bytes": 356330603, "Package": 2783860}}, "network_bandwidth": {"RX": {"Bytes": 7600, "Package": 70}, "TX": {"Bytes": 9112, "Package": 53}}}
{"timestamp": 1693163020.057727, "cpu_times": [{"user": 5222160, "nice": 70530, "sys": 5633580, "idle": 835784830, "irq": 0}, {"user": 5338320, "nice": 78290, "sys": 5605700, "idle": 834862320, "irq": 0}], "cpu_percentage": {"total": {"idle": 1890, "total": 1970, "usage": 4.060913705583758}, "cores": [{"idle": 920, "total": 980, "usage": 6.122448979591832}, {"idle": 970, "total": 990, "usage": 2.020202020202022}]}, "freemem": 7305482240, "totalmem": 8323538944, "system_uptime": 853754.04, "process_uptime": 3499.196313315, "network_stat": {"RX": {"Bytes": 3357452722, "Package": 2856764}, "TX": {"Bytes": 356339651, "Package": 2783914}}, "network_bandwidth": {"RX": {"Bytes": 7419, "Package": 68}, "TX": {"Bytes": 9048, "Package": 54}}}
{"timestamp": 1693163021.058577, "cpu_times": [{"user": 5222250, "nice": 70530, "sys": 5633600, "idle": 835785740, "irq": 0}, {"user": 5338360, "nice": 78290, "sys": 5605720, "idle": 834863250, "irq": 0}], "cpu_percentage": {"total": {"idle": 1840, "total": 2010, "usage": 8.457711442786064}, "cores": [{"idle": 910, "total": 1020, "usage": 10.784313725490192}, {"idle": 930, "total": 990, "usage": 6.060606060606055}]}, "freemem": 7305224192, "totalmem": 8323538944, "system_uptime": 853755.04, "process_uptime": 3500.197122081, "network_stat": {"RX": {"Bytes": 3357460466, "Package": 2856836}, "TX": {"Bytes": 356349046, "Package": 2783972}}, "network_bandwidth": {"RX": {"Bytes": 7744, "Package": 72}, "TX": {"Bytes": 9395, "Package": 58}}}
{"timestamp": 1693163022.059478, "cpu_times": [{"user": 5222310, "nice": 70530, "sys": 5633630, "idle": 835786660, "irq": 0}, {"user": 5338430, "nice": 78290, "sys": 5605730, "idle": 834864160, "irq": 0}], "cpu_percentage": {"total": {"idle": 1830, "total": 2000, "usage": 8.499999999999996}, "cores": [{"idle": 920, "total": 1010, "usage": 8.910891089108908}, {"idle": 910, "total": 990, "usage": 8.080808080808078}]}, "freemem": 7305531392, "totalmem": 8323538944, "system_uptime": 853756.04, "process_uptime": 3501.19805133, "network_stat": {"RX": {"Bytes": 3357467895, "Package": 2856904}, "TX": {"Bytes": 356358174, "Package": 2784026}}, "network_bandwidth": {"RX": {"Bytes": 7429, "Package": 68}, "TX": {"Bytes": 9128, "Package": 54}}}
{"timestamp": 1693163023.059971, "cpu_times": [{"user": 5222380, "nice": 70530, "sys": 5633650, "idle": 835787550, "irq": 0}, {"user": 5338460, "nice": 78290, "sys": 5605750, "idle": 834865110, "irq": 0}], "cpu_percentage": {"total": {"idle": 1840, "total": 1980, "usage": 7.070707070707072}, "cores": [{"idle": 890, "total": 980, "usage": 9.183673469387754}, {"idle": 950, "total": 1000, "usage": 5.000000000000004}]}, "freemem": 7305330688, "totalmem": 8323538944, "system_uptime": 853757.04, "process_uptime": 3502.198505093, "network_stat": {"RX": {"Bytes": 3357475676, "Package": 2856976}, "TX": {"Bytes": 356367624, "Package": 2784084}}, "network_bandwidth": {"RX": {"Bytes": 7781, "Package": 72}, "TX": {"Bytes": 9450, "Package": 58}}}
{"timestamp": 1693163024.059603, "cpu_times": [{"user": 5222480, "nice": 70530, "sys": 5633660, "idle": 835788430, "irq": 0}, {"user": 5338480, "nice": 78290, "sys": 5605750, "idle": 834866060, "irq": 0}], "cpu_percentage": {"total": {"idle": 1830, "total": 1960, "usage": 6.632653061224492}, "cores": [{"idle": 880, "total": 990, "usage": 11.111111111111116}, {"idle": 950, "total": 970, "usage": 2.0618556701030966}]}, "freemem": 7304597504, "totalmem": 8323538944, "system_uptime": 853758.04, "process_uptime": 3503.198149939, "network_stat": {"RX": {"Bytes": 3357483232, "Package": 2857045}, "TX": {"Bytes": 356377004, "Package": 2784142}}, "network_bandwidth": {"RX": {"Bytes": 7556, "Package": 69}, "TX": {"Bytes": 9380, "Package": 58}}}
{"timestamp": 1693163025.060866, "cpu_times": [{"user": 5222580, "nice": 70530, "sys": 5633680, "idle": 835789320, "irq": 0}, {"user": 5338500, "nice": 78290, "sys": 5605770, "idle": 834867010, "irq": 0}], "cpu_percentage": {"total": {"idle": 1840, "total": 2000, "usage": 7.9999999999999964}, "cores": [{"idle": 890, "total": 1010, "usage": 11.881188118811881}, {"idle": 950, "total": 990, "usage": 4.040404040404044}]}, "freemem": 7304859648, "totalmem": 8323538944, "system_uptime": 853759.04, "process_uptime": 3504.199418412, "network_stat": {"RX": {"Bytes": 3357490933, "Package": 2857116}, "TX": {"Bytes": 356386392, "Package": 2784198}}, "network_bandwidth": {"RX": {"Bytes": 7701, "Package": 71}, "TX": {"Bytes": 9388, "Package": 56}}}
{"timestamp": 1693163026.061488, "cpu_times": [{"user": 5222590, "nice": 70530, "sys": 5633690, "idle": 835790280, "irq": 0}, {"user": 5338580, "nice": 78290, "sys": 5605780, "idle": 834867880, "irq": 0}], "cpu_percentage": {"total": {"idle": 1830, "total": 1940, "usage": 5.670103092783507}, "cores": [{"idle": 960, "total": 980, "usage": 2.0408163265306145}, {"idle": 870, "total": 960, "usage": 9.375}]}, "freemem": 7304601600, "totalmem": 8323538944, "system_uptime": 853760.04, "process_uptime": 3505.200050725, "network_stat": {"RX": {"Bytes": 3357498459, "Package": 2857185}, "TX": {"Bytes": 356395359, "Package": 2784250}}, "network_bandwidth": {"RX": {"Bytes": 7526, "Package": 69}, "TX": {"Bytes": 8967, "Package": 52}}}
{"timestamp": 1693163027.06285, "cpu_times": [{"user": 5222590, "nice": 70530, "sys": 5633700, "idle": 835791270, "irq": 0}, {"user": 5338610, "nice": 78290, "sys": 5605780, "idle": 834868820, "irq": 0}], "cpu_percentage": {"total": {"idle": 1930, "total": 1970, "usage": 2.030456852791873}, "cores": [{"idle": 990, "total": 1000, "usage": 1.0000000000000009}, {"idle": 940, "total": 970, "usage": 3.0927835051546393}]}, "freemem": 7304114176, "totalmem": 8323538944, "system_uptime": 853761.05, "process_uptime": 3506.20142482, "network_stat": {"RX": {"Bytes": 3357502428, "Package": 2857210}, "TX": {"Bytes": 356398864, "Package": 2784269}}, "network_bandwidth": {"RX": {"Bytes": 3969, "Package": 25}, "TX": {"Bytes": 3505, "Package": 19}}}
{"timestamp": 1693163028.064078, "cpu_times": [{"user": 5222590, "nice": 70530, "sys": 5633710, "idle": 835792260, "irq": 0}, {"user": 5338620, "nice": 78290, "sys": 5605780, "idle": 834869790, "irq": 0}], "cpu_percentage": {"total": {"idle": 1960, "total": 1980, "usage": 1.0101010101010055}, "cores": [{"idle": 990, "total": 1000, "usage": 1.0000000000000009}, {"idle": 970, "total": 980, "usage": 1.0204081632653073}]}, "freemem": 7304630272, "totalmem": 8323538944, "system_uptime": 853762.05, "process_uptime": 3507.202623203, "network_stat": {"RX": {"Bytes": 3357504636, "Package": 2857213}, "TX": {"Bytes": 356399731, "Package": 2784272}}, "network_bandwidth": {"RX": {"Bytes": 2208, "Package": 3}, "TX": {"Bytes": 867, "Package": 3}}}
{"timestamp": 1693163029.065608, "cpu_times": [{"user": 5222600, "nice": 70530, "sys": 5633710, "idle": 835793250, "irq": 0}, {"user": 5338620, "nice": 78290, "sys": 5605800, "idle": 834870770, "irq": 0}], "cpu_percentage": {"total": {"idle": 1970, "total": 2000, "usage": 1.5000000000000013}, "cores": [{"idle": 990, "total": 1000, "usage": 1.0000000000000009}, {"idle": 980, "total": 1000, "usage": 2.0000000000000018}]}, "freemem": 7303368704, "totalmem": 8323538944, "system_uptime": 853763.05, "process_uptime": 3508.20417851, "network_stat": {"RX": {"Bytes": 3357508289, "Package": 2857222}, "TX": {"Bytes": 356402126, "Package": 2784281}}, "network_bandwidth": {"RX": {"Bytes": 3653, "Package": 9}, "TX": {"Bytes": 2395, "Package": 9}}}
{"timestamp": 1693163030.066588, "cpu_times": [{"user": 5222600, "nice": 70530, "sys": 5633720, "idle": 835794220, "irq": 0}, {"user": 5338630, "nice": 78290, "sys": 5605800, "idle": 834871750, "irq": 0}], "cpu_percentage": {"total": {"idle": 1950, "total": 1970, "usage": 1.0152284263959421}, "cores": [{"idle": 970, "total": 980, "usage": 1.0204081632653073}, {"idle": 980, "total": 990, "usage": 1.0101010101010055}]}, "freemem": 7303626752, "totalmem": 8323538944, "system_uptime": 853764.05, "process_uptime": 3509.205176152, "network_stat": {"RX": {"Bytes": 3357511095, "Package": 2857231}, "TX": {"Bytes": 356404040, "Package": 2784291}}, "network_bandwidth": {"RX": {"Bytes": 2806, "Package": 9}, "TX": {"Bytes": 1914, "Package": 10}}}
{"timestamp": 1693163031.067984, "cpu_times": [{"user": 5222600, "nice": 70530, "sys": 5633730, "idle": 835795220, "irq": 0}, {"user": 5338630, "nice": 78290, "sys": 5605800, "idle": 834872720, "irq": 0}], "cpu_percentage": {"total": {"idle": 1970, "total": 1980, "usage": 0.5050505050505083}, "cores": [{"idle": 1000, "total": 1010, "usage": 0.990099009900991}, {"idle": 970, "total": 970, "usage": 0}]}, "freemem": 7302594560, "totalmem": 8323538944, "system_uptime": 853765.05, "process_uptime": 3510.206530892, "network_stat": {"RX": {"Bytes": 3357513284, "Package": 2857234}, "TX": {"Bytes": 356404908, "Package": 2784294}}, "network_bandwidth": {"RX": {"Bytes": 2189, "Package": 3}, "TX": {"Bytes": 868, "Package": 3}}}
