{"timestamp": 1692404386.737784, "cpu_times": [{"user": 1629990, "nice": 60, "sys": 1510160, "idle": 274209810, "irq": 0}, {"user": 2180870, "nice": 220, "sys": 1503540, "idle": 273466630, "irq": 0}, {"user": 2160580, "nice": 200, "sys": 1522230, "idle": 273370960, "irq": 0}, {"user": 1994070, "nice": 360, "sys": 1335690, "idle": 274203730, "irq": 0}], "cpu_percentage": {"total": {"idle": 3860, "total": 3960, "usage": 2.5252525252525304}, "cores": [{"idle": 960, "total": 990, "usage": 3.0303030303030276}, {"idle": 980, "total": 990, "usage": 1.0101010101010055}, {"idle": 940, "total": 980, "usage": 4.081632653061229}, {"idle": 980, "total": 1000, "usage": 2.0000000000000018}]}, "freemem": 7530307584, "totalmem": 8191840256, "system_uptime": 278287.34, "process_uptime": 5489.032089912, "network_stat": {"RX": {"Bytes": 156642480, "Package": 1442199}, "TX": {"Bytes": 342363498, "Package": 1151141}}, "network_bandwidth": {"RX": {"Bytes": 2560, "Package": 25}, "TX": {"Bytes": 3037, "Package": 22}}}
{"timestamp": 1692404387.738164, "cpu_times": [{"user": 1630010, "nice": 60, "sys": 1510180, "idle": 274210760, "irq": 0}, {"user": 2180910, "nice": 220, "sys": 1503570, "idle": 273467560, "irq": 0}, {"user": 2160620, "nice": 200, "sys": 1522250, "idle": 273371890, "irq": 0}, {"user": 1994120, "nice": 360, "sys": 1335710, "idle": 274204640, "irq": 0}], "cpu_percentage": {"total": {"idle": 3720, "total": 3960, "usage": 6.060606060606055}, "cores": [{"idle": 950, "total": 990, "usage": 4.040404040404044}, {"idle": 930, "total": 1000, "usage": 6.999999999999995}, {"idle": 930, "total": 990, "usage": 6.060606060606055}, {"idle": 910, "total": 980, "usage": 7.14285714285714}]}, "freemem": 7530569728, "totalmem": 8191840256, "system_uptime": 278288.34, "process_uptime": 5490.032733113, "network_stat": {"RX": {"Bytes": 156646292, "Package": 1442243}, "TX": {"Bytes": 342372289, "Package": 1151185}}, "network_bandwidth": {"RX": {"Bytes": 3812, "Package": 44}, "TX": {"Bytes": 8791, "Package": 44}}}
{"timestamp": 1692404388.739109, "cpu_times": [{"user": 1630060, "nice": 60, "sys": 1510220, "idle": 274211660, "irq": 0}, {"user": 2180950, "nice": 220, "sys": 1503600, "idle": 273468460, "irq": 0}, {"user": 2160660, "nice": 200, "sys": 1522260, "idle": 273372820, "irq": 0}, {"user": 1994170, "nice": 360, "sys": 1335740, "idle": 274205580, "irq": 0}], "cpu_percentage": {"total": {"idle": 3670, "total": 3960, "usage": 7.32323232323232}, "cores": [{"idle": 900, "total": 990, "usage": 9.090909090909093}, {"idle": 900, "total": 970, "usage": 7.216494845360821}, {"idle": 930, "total": 980, "usage": 5.102040816326525}, {"idle": 940, "total": 1020, "usage": 7.843137254901967}]}, "freemem": 7531372544, "totalmem": 8191840256, "system_uptime": 278289.34, "process_uptime": 5491.033717886, "network_stat": {"RX": {"Bytes": 156651060, "Package": 1442298}, "TX": {"Bytes": 342382387, "Package": 1151238}}, "network_bandwidth": {"RX": {"Bytes": 4768, "Package": 55}, "TX": {"Bytes": 10098, "Package": 53}}}
{"timestamp": 1692404389.739922, "cpu_times": [{"user": 1630120, "nice": 60, "sys": 1510240, "idle": 274212570, "irq": 0}, {"user": 2181020, "nice": 220, "sys": 1503610, "idle": 273469390, "irq": 0}, {"user": 2160700, "nice": 200, "sys": 1522270, "idle": 273373740, "irq": 0}, {"user": 1994220, "nice": 360, "sys": 1335740, "idle": 274206490, "irq": 0}], "cpu_percentage": {"total": {"idle": 3670, "total": 3930, "usage": 6.61577608142494}, "cores": [{"idle": 910, "total": 990, "usage": 8.080808080808078}, {"idle": 930, "total": 1010, "usage": 7.920792079207917}, {"idle": 920, "total": 970, "usage": 5.154639175257736}, {"idle": 910, "total": 960, "usage": 5.2083333333333375}]}, "freemem": 7531372544, "totalmem": 8191840256, "system_uptime": 278290.34, "process_uptime": 5492.034575197, "network_stat": {"RX": {"Bytes": 156655628, "Package": 1442349}, "TX": {"Bytes": 342392526, "Package": 1151289}}, "network_bandwidth": {"RX": {"Bytes": 4568, "Package": 51}, "TX": {"Bytes": 10139, "Package": 51}}}
{"timestamp": 1692404390.740841, "cpu_times": [{"user": 1630180, "nice": 60, "sys": 1510240, "idle": 274213500, "irq": 0}, {"user": 2181050, "nice": 220, "sys": 1503640, "idle": 273470310, "irq": 0}, {"user": 2160750, "nice": 200, "sys": 1522290, "idle": 273374650, "irq": 0}, {"user": 1994260, "nice": 360, "sys": 1335760, "idle": 274207400, "irq": 0}], "cpu_percentage": {"total": {"idle": 3670, "total": 3920, "usage": 6.377551020408168}, "cores": [{"idle": 930, "total": 990, "usage": 6.060606060606055}, {"idle": 920, "total": 980, "usage": 6.122448979591832}, {"idle": 910, "total": 980, "usage": 7.14285714285714}, {"idle": 910, "total": 970, "usage": 6.185567010309279}]}, "freemem": 7530885120, "totalmem": 8191840256, "system_uptime": 278291.34, "process_uptime": 5493.035441008, "network_stat": {"RX": {"Bytes": 156660384, "Package": 1442404}, "TX": {"Bytes": 342402814, "Package": 1151344}}, "network_bandwidth": {"RX": {"Bytes": 4756, "Package": 55}, "TX": {"Bytes": 10288, "Package": 55}}}
{"timestamp": 1692404391.740467, "cpu_times": [{"user": 1630290, "nice": 60, "sys": 1510260, "idle": 274214380, "irq": 0}, {"user": 2181070, "nice": 220, "sys": 1503660, "idle": 273471250, "irq": 0}, {"user": 2160860, "nice": 200, "sys": 1522310, "idle": 273375490, "irq": 0}, {"user": 1994300, "nice": 360, "sys": 1335780, "idle": 274208330, "irq": 0}], "cpu_percentage": {"total": {"idle": 3590, "total": 3950, "usage": 9.113924050632916}, "cores": [{"idle": 880, "total": 1010, "usage": 12.871287128712872}, {"idle": 940, "total": 980, "usage": 4.081632653061229}, {"idle": 840, "total": 970, "usage": 13.4020618556701}, {"idle": 930, "total": 990, "usage": 6.060606060606055}]}, "freemem": 7530377216, "totalmem": 8191840256, "system_uptime": 278292.34, "process_uptime": 5494.034898222, "network_stat": {"RX": {"Bytes": 156667564, "Package": 1442465}, "TX": {"Bytes": 342413095, "Package": 1151399}}, "network_bandwidth": {"RX": {"Bytes": 7180, "Package": 61}, "TX": {"Bytes": 10281, "Package": 55}}}
{"timestamp": 1692404392.741205, "cpu_times": [{"user": 1630310, "nice": 60, "sys": 1510290, "idle": 274215320, "irq": 0}, {"user": 2181140, "nice": 220, "sys": 1503660, "idle": 273472170, "irq": 0}, {"user": 2161070, "nice": 200, "sys": 1522350, "idle": 273376220, "irq": 0}, {"user": 1994380, "nice": 360, "sys": 1335800, "idle": 274209240, "irq": 0}], "cpu_percentage": {"total": {"idle": 3500, "total": 3970, "usage": 11.838790931989928}, "cores": [{"idle": 940, "total": 990, "usage": 5.05050505050505}, {"idle": 920, "total": 990, "usage": 7.070707070707072}, {"idle": 730, "total": 980, "usage": 25.510204081632647}, {"idle": 910, "total": 1010, "usage": 9.9009900990099}]}, "freemem": 7530663936, "totalmem": 8191840256, "system_uptime": 278293.34, "process_uptime": 5495.035794497, "network_stat": {"RX": {"Bytes": 156672200, "Package": 1442519}, "TX": {"Bytes": 342423252, "Package": 1151452}}, "network_bandwidth": {"RX": {"Bytes": 4636, "Package": 54}, "TX": {"Bytes": 10157, "Package": 53}}}
{"timestamp": 1692404393.742896, "cpu_times": [{"user": 1630360, "nice": 60, "sys": 1510310, "idle": 274216220, "irq": 0}, {"user": 2181370, "nice": 220, "sys": 1503680, "idle": 273472910, "irq": 0}, {"user": 2161090, "nice": 200, "sys": 1522370, "idle": 273377150, "irq": 0}, {"user": 1994430, "nice": 360, "sys": 1335830, "idle": 274210180, "irq": 0}], "cpu_percentage": {"total": {"idle": 3510, "total": 3950, "usage": 11.139240506329118}, "cores": [{"idle": 900, "total": 970, "usage": 7.216494845360821}, {"idle": 740, "total": 990, "usage": 25.25252525252525}, {"idle": 930, "total": 970, "usage": 4.123711340206182}, {"idle": 940, "total": 1020, "usage": 7.843137254901967}]}, "freemem": 7530315776, "totalmem": 8191840256, "system_uptime": 278294.34, "process_uptime": 5496.037236377, "network_stat": {"RX": {"Bytes": 156677554, "Package": 1442575}, "TX": {"Bytes": 342433355, "Package": 1151504}}, "network_bandwidth": {"RX": {"Bytes": 5354, "Package": 56}, "TX": {"Bytes": 10103, "Package": 52}}}
{"timestamp": 1692404394.74318, "cpu_times": [{"user": 1630390, "nice": 60, "sys": 1510340, "idle": 274217160, "irq": 0}, {"user": 2181430, "nice": 220, "sys": 1503700, "idle": 273473820, "irq": 0}, {"user": 2161210, "nice": 200, "sys": 1522380, "idle": 273377980, "irq": 0}, {"user": 1994560, "nice": 360, "sys": 1335850, "idle": 274211010, "irq": 0}], "cpu_percentage": {"total": {"idle": 3510, "total": 3930, "usage": 10.687022900763354}, "cores": [{"idle": 940, "total": 1000, "usage": 6.000000000000005}, {"idle": 910, "total": 990, "usage": 8.080808080808078}, {"idle": 830, "total": 960, "usage": 13.541666666666663}, {"idle": 830, "total": 980, "usage": 15.306122448979586}]}, "freemem": 7530561536, "totalmem": 8191840256, "system_uptime": 278295.34, "process_uptime": 5497.037521362, "network_stat": {"RX": {"Bytes": 156684272, "Package": 1442636}, "TX": {"Bytes": 342443468, "Package": 1151556}}, "network_bandwidth": {"RX": {"Bytes": 6718, "Package": 61}, "TX": {"Bytes": 10113, "Package": 52}}}
{"timestamp": 1692404395.744301, "cpu_times": [{"user": 1630460, "nice": 60, "sys": 1510350, "idle": 274218090, "irq": 0}, {"user": 2181470, "nice": 220, "sys": 1503720, "idle": 273474740, "irq": 0}, {"user": 2161260, "nice": 200, "sys": 1522420, "idle": 273378880, "irq": 0}, {"user": 1994760, "nice": 360, "sys": 1335870, "idle": 274211760, "irq": 0}], "cpu_percentage": {"total": {"idle": 3500, "total": 3950, "usage": 11.392405063291145}, "cores": [{"idle": 930, "total": 1010, "usage": 7.920792079207917}, {"idle": 920, "total": 980, "usage": 6.122448979591832}, {"idle": 900, "total": 990, "usage": 9.090909090909093}, {"idle": 750, "total": 970, "usage": 22.680412371134018}]}, "freemem": 7529603072, "totalmem": 8191840256, "system_uptime": 278296.34, "process_uptime": 5498.038679042, "network_stat": {"RX": {"Bytes": 156691044, "Package": 1442697}, "TX": {"Bytes": 342453790, "Package": 1151611}}, "network_bandwidth": {"RX": {"Bytes": 6772, "Package": 61}, "TX": {"Bytes": 10322, "Package": 55}}}
{"timestamp": 1692404396.745551, "cpu_times": [{"user": 1630620, "nice": 60, "sys": 1510360, "idle": 274218890, "irq": 0}, {"user": 2181510, "nice": 220, "sys": 1503740, "idle": 273475660, "irq": 0}, {"user": 2161280, "nice": 200, "sys": 1522450, "idle": 273379800, "irq": 0}, {"user": 1994870, "nice": 360, "sys": 1335890, "idle": 274212640, "irq": 0}], "cpu_percentage": {"total": {"idle": 3520, "total": 3930, "usage": 10.432569974554706}, "cores": [{"idle": 800, "total": 970, "usage": 17.525773195876294}, {"idle": 920, "total": 980, "usage": 6.122448979591832}, {"idle": 920, "total": 970, "usage": 5.154639175257736}, {"idle": 880, "total": 1010, "usage": 12.871287128712872}]}, "freemem": 7527567360, "totalmem": 8191840256, "system_uptime": 278297.34, "process_uptime": 5499.039901351, "network_stat": {"RX": {"Bytes": 156696752, "Package": 1442751}, "TX": {"Bytes": 342463898, "Package": 1151663}}, "network_bandwidth": {"RX": {"Bytes": 5708, "Package": 54}, "TX": {"Bytes": 10108, "Package": 52}}}
{"timestamp": 1692404397.746986, "cpu_times": [{"user": 1630640, "nice": 60, "sys": 1510380, "idle": 274219850, "irq": 0}, {"user": 2181520, "nice": 220, "sys": 1503750, "idle": 273476620, "irq": 0}, {"user": 2161460, "nice": 200, "sys": 1522470, "idle": 273380590, "irq": 0}, {"user": 1994910, "nice": 360, "sys": 1335900, "idle": 274213590, "irq": 0}], "cpu_percentage": {"total": {"idle": 3660, "total": 3970, "usage": 7.8085642317380355}, "cores": [{"idle": 960, "total": 1000, "usage": 4.0000000000000036}, {"idle": 960, "total": 980, "usage": 2.0408163265306145}, {"idle": 790, "total": 990, "usage": 20.2020202020202}, {"idle": 950, "total": 1000, "usage": 5.000000000000004}]}, "freemem": 7527862272, "totalmem": 8191840256, "system_uptime": 278298.35, "process_uptime": 5500.041682896, "network_stat": {"RX": {"Bytes": 156700235, "Package": 1442793}, "TX": {"Bytes": 342471542, "Package": 1151704}}, "network_bandwidth": {"RX": {"Bytes": 3483, "Package": 42}, "TX": {"Bytes": 7644, "Package": 41}}}
{"timestamp": 1692404398.747997, "cpu_times": [{"user": 1630640, "nice": 60, "sys": 1510400, "idle": 274220790, "irq": 0}, {"user": 2181520, "nice": 220, "sys": 1503760, "idle": 273477610, "irq": 0}, {"user": 2161460, "nice": 200, "sys": 1522470, "idle": 273381580, "irq": 0}, {"user": 1994910, "nice": 360, "sys": 1335910, "idle": 274214580, "irq": 0}], "cpu_percentage": {"total": {"idle": 3910, "total": 3950, "usage": 1.0126582278481067}, "cores": [{"idle": 940, "total": 960, "usage": 2.083333333333337}, {"idle": 990, "total": 1000, "usage": 1.0000000000000009}, {"idle": 990, "total": 990, "usage": 0}, {"idle": 990, "total": 1000, "usage": 1.0000000000000009}]}, "freemem": 7527608320, "totalmem": 8191840256, "system_uptime": 278299.35, "process_uptime": 5501.042772966, "network_stat": {"RX": {"Bytes": 156700931, "Package": 1442799}, "TX": {"Bytes": 342473378, "Package": 1151706}}, "network_bandwidth": {"RX": {"Bytes": 696, "Package": 6}, "TX": {"Bytes": 1836, "Package": 2}}}
{"timestamp": 1692404399.748962, "cpu_times": [{"user": 1630640, "nice": 60, "sys": 1510420, "idle": 274221780, "irq": 0}, {"user": 2181530, "nice": 220, "sys": 1503760, "idle": 273478600, "irq": 0}, {"user": 2161470, "nice": 200, "sys": 1522490, "idle": 273382540, "irq": 0}, {"user": 1994910, "nice": 360, "sys": 1335920, "idle": 274215570, "irq": 0}], "cpu_percentage": {"total": {"idle": 3930, "total": 4000, "usage": 1.749999999999996}, "cores": [{"idle": 990, "total": 1010, "usage": 1.980198019801982}, {"idle": 990, "total": 1000, "usage": 1.0000000000000009}, {"idle": 960, "total": 990, "usage": 3.0303030303030276}, {"idle": 990, "total": 1000, "usage": 1.0000000000000009}]}, "freemem": 7527608320, "totalmem": 8191840256, "system_uptime": 278300.35, "process_uptime": 5502.043526299, "network_stat": {"RX": {"Bytes": 156701057, "Package": 1442801}, "TX": {"Bytes": 342475215, "Package": 1151708}}, "network_bandwidth": {"RX": {"Bytes": 126, "Package": 2}, "TX": {"Bytes": 1837, "Package": 2}}}
{"timestamp": 1692404400.749456, "cpu_times": [{"user": 1630650, "nice": 60, "sys": 1510420, "idle": 274222770, "irq": 0}, {"user": 2181540, "nice": 220, "sys": 1503770, "idle": 273479560, "irq": 0}, {"user": 2161480, "nice": 200, "sys": 1522490, "idle": 273383520, "irq": 0}, {"user": 1994910, "nice": 360, "sys": 1335920, "idle": 274216560, "irq": 0}], "cpu_percentage": {"total": {"idle": 3920, "total": 3960, "usage": 1.0101010101010055}, "cores": [{"idle": 990, "total": 1000, "usage": 1.0000000000000009}, {"idle": 960, "total": 980, "usage": 2.0408163265306145}, {"idle": 980, "total": 990, "usage": 1.0101010101010055}, {"idle": 990, "total": 990, "usage": 0}]}, "freemem": 7527616512, "totalmem": 8191840256, "system_uptime": 278301.35, "process_uptime": 5503.044132485, "network_stat": {"RX": {"Bytes": 156702450, "Package": 1442807}, "TX": {"Bytes": 342477120, "Package": 1151711}}, "network_bandwidth": {"RX": {"Bytes": 1393, "Package": 6}, "TX": {"Bytes": 1905, "Package": 3}}}
{"timestamp": 1692404401.750206, "cpu_times": [{"user": 1630650, "nice": 60, "sys": 1510420, "idle": 274223750, "irq": 0}, {"user": 2181550, "nice": 220, "sys": 1503800, "idle": 273480520, "irq": 0}, {"user": 2161480, "nice": 200, "sys": 1522500, "idle": 273384500, "irq": 0}, {"user": 1994910, "nice": 360, "sys": 1335940, "idle": 274217550, "irq": 0}], "cpu_percentage": {"total": {"idle": 3910, "total": 3980, "usage": 1.7587939698492483}, "cores": [{"idle": 980, "total": 980, "usage": 0}, {"idle": 960, "total": 1000, "usage": 4.0000000000000036}, {"idle": 980, "total": 990, "usage": 1.0101010101010055}, {"idle": 990, "total": 1010, "usage": 1.980198019801982}]}, "freemem": 7527100416, "totalmem": 8191840256, "system_uptime": 278302.35, "process_uptime": 5504.044844301, "network_stat": {"RX": {"Bytes": 156702654, "Package": 1442810}, "TX": {"Bytes": 342479043, "Package": 1151714}}, "network_bandwidth": {"RX": {"Bytes": 204, "Package": 3}, "TX": {"Bytes": 1923, "Package": 3}}}
